.scrutinizer.yml
.travis.yml
LICENSE
MANIFEST.in
README.rst
setup.cfg
setup.py
df3tools/__init__.py
df3tools/df3combine.py
df3tools/df3split.py
df3tools/exceptions.py
df3tools.egg-info/PKG-INFO
df3tools.egg-info/SOURCES.txt
df3tools.egg-info/dependency_links.txt
df3tools.egg-info/entry_points.txt
df3tools.egg-info/pbr.json
df3tools.egg-info/requires.txt
df3tools.egg-info/top_level.txt