Metadata-Version: 1.1
Name: df3tools
Version: 0.1.0
Summary: Tools to convert Pov-Ray DF3 files to set of images and vice versa
Home-page: https://github.com/a5kin/df3tools
Author: Andrey Zamaraev
Author-email: a5kin@github.com
License: MIT
Keywords: povray pov-ray density file df3 commandline tools utils utility
Platform: UNKNOWN
Classifier: Development Status :: 3 - Alpha
Classifier: Environment :: Console
Classifier: Topic :: Artistic Software
Classifier: Topic :: Multimedia :: Graphics :: 3D Modeling
Classifier: Topic :: Multimedia :: Graphics :: 3D Rendering
Classifier: Topic :: Utilities
Classifier: License :: OSI Approved :: MIT License
Classifier: Programming Language :: Python :: 2
Classifier: Programming Language :: Python :: 2.7
Classifier: Programming Language :: Python :: 3
Classifier: Programming Language :: Python :: 3.3
Classifier: Programming Language :: Python :: 3.4
Classifier: Programming Language :: Python :: 3.5
Classifier: Programming Language :: Python :: 3.6
Classifier: Programming Language :: Python :: Implementation :: PyPy
